torch_fn/__init__.py
torch_fn/_torch_fn.py
torch_fn-1.0.0.dist-info/LICENSE
torch_fn-1.0.0.dist-info/METADATA
torch_fn-1.0.0.dist-info/WHEEL
torch_fn-1.0.0.dist-info/top_level.txt
torch_fn-1.0.0.dist-info/RECORD
